{
    "type": "Feature",
    "properties": {
        "id": 2178990,
        "category": "Projet Tourisme",
        "name": "OT Pays Tarusate",
        "description": "Projet qui démarre par le tourisme avec la volonté d’ouvrir le jeu vers la collectivité territoriale",
        "website": "https://www.teritorio.fr/projets/la-cartographie-en-pays-tarusate-un-projet-danimation-du-territoire/",
        "image": [
            "https://www.lecoeurdeslandes.com/files/img/accueil/carte-pays-tarusate.jpg"
        ],
        "id zone OSM": "2178990",
        "id poi": "",
        "remarque": "",
        "category_ids": "22",
        "metadata": {
            "id": 2178990,
            "category_ids": [
                22
            ]
        },
        "editorial": {
            "website:details": "https://www.teritorio.fr/projets/la-cartographie-en-pays-tarusate-un-projet-danimation-du-territoire/",
            "popup_fields": [
                {
                    "field": "description"
                }
            ]
        },
        "display": {
            "icon": "teritorio teritorio-office",
            "color_fill": "#e50980",
            "color_line": "#e50980"
        }
    },
    "geometry": {
        "type": "Point",
        "coordinates": [
            -0.779936222147197,
            43.831119081026316
        ]
    }
}