{
    "type": "Feature",
    "properties": {
        "id": 2178970,
        "category": "Projet Tourisme",
        "name": "OTi de Mimizan",
        "description": "Projet de carte Web dans la foulée de la participation au projet départemental",
        "website": "https://www.teritorio.fr/projets/la-carte-de-mimizan/",
        "image": [
            "https://www.teritorio.fr/wp-content/uploads/2022/07/mimizan.jpg"
        ],
        "id zone OSM": "2178970",
        "id poi": "",
        "remarque": "",
        "category_ids": "22",
        "metadata": {
            "id": 2178970,
            "category_ids": [
                22
            ]
        },
        "editorial": {
            "website:details": "https://www.teritorio.fr/projets/la-carte-de-mimizan/",
            "popup_fields": [
                {
                    "field": "description"
                }
            ]
        },
        "display": {
            "icon": "teritorio teritorio-office",
            "color_fill": "#e50980",
            "color_line": "#e50980"
        }
    },
    "geometry": {
        "type": "Point",
        "coordinates": [
            -1.1449820257201655,
            44.11750677109054
        ]
    }
}