{
    "type": "Feature",
    "properties": {
        "id": 6849463,
        "category": "Projet Ville & Tourisme",
        "name": "Communautés de communes – COCM",
        "description": "Cart’info, un projet au service de l’information des résidents, un bel effort de contribution de la collectivité",
        "website": "https://www.teritorio.fr/projets/cocm-manche-cartinfo/",
        "image": [
            "https://www.teritorio.fr/wp-content/uploads/2022/07/cocm.png"
        ],
        "id zone OSM": "6849463",
        "id poi": "",
        "remarque": "",
        "category_ids": "23",
        "metadata": {
            "id": 6849463,
            "category_ids": [
                23
            ]
        },
        "editorial": {
            "website:details": "https://www.teritorio.fr/projets/cocm-manche-cartinfo/",
            "popup_fields": [
                {
                    "field": "description"
                }
            ],
            "class_label": {
                "en": "City & Tourism Projects",
                "fr": "Projets ville & tourisme"
            }
        },
        "display": {
            "icon": "teritorio teritorio-extra-town",
            "color_fill": "#2a62ac",
            "color_line": "#2a62ac"
        }
    },
    "geometry": {
        "type": "Point",
        "coordinates": [
            -1.432116036641927,
            49.240804192331446
        ]
    }
}