{
    "type": "Feature",
    "properties": {
        "id": 6983400,
        "category": "Projet Culture",
        "name": "Agglomération du Pays-Basque",
        "description": "Cartographie du Street-Art – Bayonne et environs",
        "website": "https://www.teritorio.fr/projets/une-carte-du-street-art-pour-le-festival-point-de-vue/",
        "image": [
            "https://www.pointsdevue.eus/wp-content/uploads/2021/10/mural.jpg"
        ],
        "id zone OSM": "6983400",
        "id poi": "",
        "remarque": "",
        "category_ids": "26",
        "metadata": {
            "id": 6983400,
            "category_ids": [
                26
            ]
        },
        "editorial": {
            "website:details": "https://www.teritorio.fr/projets/une-carte-du-street-art-pour-le-festival-point-de-vue/",
            "popup_fields": [
                {
                    "field": "description"
                }
            ]
        },
        "display": {
            "icon": "teritorio teritorio-extra-recycling",
            "color_fill": "#f25c05",
            "color_line": "#f25c05"
        }
    },
    "geometry": {
        "type": "Feature",
        "properties": {
        },
        "geometry": {
            "type": "Point",
            "coordinates": [
                -1.2433531184610223,
                43.304943685003956
            ]
        }
    }
}