{
    "type": "Feature",
    "properties": {
        "id": 6983400,
        "category": "Projet Culture",
        "name": "Agglomération du Pays-Basque",
        "description": "Depuis 2019, cartographie du Street-Art dans le cadre du Festival Point de Vue – Bayonne, puis environs.",
        "image": [
            "https://www.pointsdevue.eus/wp-content/uploads/2021/10/mural.jpg"
        ],
        "id zone OSM": "6983400",
        "id poi": "",
        "remarque": "",
        "category_ids": "26",
        "metadata": {
            "id": 6983400,
            "category_ids": [
                26
            ]
        },
        "editorial": {
            "website:details": null,
            "popup_fields": [
                {
                    "field": "description"
                }
            ],
            "class_label": {
                "en": "Cultural Projects",
                "fr": "Projets culturel"
            }
        },
        "display": {
            "icon": "teritorio teritorio-artwork",
            "color_fill": "#76009e",
            "color_line": "#76009e"
        }
    },
    "geometry": {
        "type": "Point",
        "coordinates": [
            -1.2433531184610223,
            43.304943685003956
        ]
    }
}