{
    "type": "FeatureCollection",
    "features": [
        {
            "type": "Feature",
            "properties": {
                "id": 4713026065,
                "category": "Projet Transition",
                "name": "Bordeaux Métropole -  Grand Projet des Villes Rive Droite ",
                "description": "Projet de cartophie des projets de logements, d'équipements, d'aménagements urbains ou économiques sur la Rive Droite",
                "website": "https://www.teritorio.fr/projets/la-carte-des-grands-projets-de-la-rive-droite-bordeaux/",
                "image": [
                    "https://www.surlarivedroite.fr/wp-content/uploads/2020/09/Une-vignette-e1600785542756.jpg"
                ],
                "id zone OSM": "",
                "id poi": "4713026065",
                "remarque": "il faudrait un polygonne spécifique groupant toutes les villes",
                "category_ids": "25",
                "metadata": {
                    "id": 4713026065,
                    "category_ids": [
                        25
                    ]
                },
                "editorial": {
                    "website:details": "https://www.teritorio.fr/projets/la-carte-des-grands-projets-de-la-rive-droite-bordeaux/",
                    "popup_fields": [
                        {
                            "field": "description"
                        }
                    ],
                    "class_label": {
                        "en": "Transition Projects",
                        "fr": "Projets transition"
                    }
                },
                "display": {
                    "icon": "teritorio teritorio-extra-recycling",
                    "color_fill": "#f25c05",
                    "color_line": "#f25c05"
                }
            },
            "geometry": {
                "type": "Point",
                "coordinates": [
                    -0.528046,
                    44.852756
                ]
            }
        },
        {
            "type": "Feature",
            "properties": {
                "name": "PETR - Pays Adour Lances Océanes",
                "description": "Réalisation d'une cartographie pour le Projet Alimentaire du Pays ALO (4 communautés de communes du Sud des Landes) - La donnée OSM sert de pivot, articulée à de la donnée métier. Implication de 80 acteurs pour la contribution.",
                "category": "Projet Transition",
                "category_ids": "25",
                "image": [
                    "https://www.teritorio.fr/wp-content/uploads/2022/09/pat.png"
                ],
                "website": "https://www.teritorio.fr/projets/alimentation-territoire-la-donnee-ouverte-au-coeur-du-projet-du-pays-adour-landes-oceanes/",
                "metadata": {
                    "id": null,
                    "category_ids": [
                        25
                    ]
                },
                "editorial": {
                    "website:details": "https://www.teritorio.fr/projets/alimentation-territoire-la-donnee-ouverte-au-coeur-du-projet-du-pays-adour-landes-oceanes/",
                    "popup_fields": [
                        {
                            "field": "description"
                        }
                    ],
                    "class_label": {
                        "en": "Transition Projects",
                        "fr": "Projets transition"
                    }
                },
                "display": {
                    "icon": "teritorio teritorio-extra-recycling",
                    "color_fill": "#f25c05",
                    "color_line": "#f25c05"
                }
            },
            "geometry": {
                "type": "Point",
                "coordinates": [
                    -1.1218135805318603,
                    43.629294098845996
                ]
            }
        }
    ]
}